{"name":"vTweet","tagline":"A PHP/HTML5/CSS/JS Desktop/Web Twitter Client!","body":"vTweet\r\n=========\r\n\r\nvTweet (VSTweet) is a HTML5 and Javascript based Desktop/Web Twitter Client.\r\n\r\nFeatures\r\n----\r\n\r\n- Multi-User support.\r\n- Same-Client DM Read marking Support.\r\n- Encrypt DMs too other Users.\r\n- And many more...\r\n\r\n\r\nVersion\r\n----\r\n\r\n1.0 Pre-Alpha\r\n\r\nInternals\r\n-----------\r\n\r\nvTweet uses a number of open source projects to work properly:\r\n\r\n* [Twitter Bootstrap] - great UI boilerplate for modern web apps\r\n* [jQuery] - duh\r\n* [HTML5] - Because it's better than HTML4\r\n* [PHP] - For Easy \"Server-side\" implementation.\r\n* [Javascript] - this is an easy one.\r\n\r\nLicense\r\n----\r\n\r\nGNUGPLv3\r\n\r\n    ","google":"","note":"Don't delete this file! It's used internally to help with page regeneration."}